Leer_PDF_GP/Funciones.py
Leer_PDF_GP/__init__.py
Leer_PDF_GP-1.0.0.dist-info/METADATA
Leer_PDF_GP-1.0.0.dist-info/WHEEL
Leer_PDF_GP-1.0.0.dist-info/top_level.txt
Leer_PDF_GP-1.0.0.dist-info/RECORD
