Metadata-Version: 2.1
Name: Leer-PDF-GP
Version: 1.0.0
Summary: Librería para leer ficheros PDFs y extraer la información en formato str
Home-page: https://github.com
Author: Ander Valencia
Author-email: a@gmail.com
License: MIT
